jsonpare/__init__.py
jsonpare-0.2.8.data/scripts/jp
jsonpare-0.2.8.dist-info/DESCRIPTION.rst
jsonpare-0.2.8.dist-info/METADATA
jsonpare-0.2.8.dist-info/metadata.json
jsonpare-0.2.8.dist-info/RECORD
jsonpare-0.2.8.dist-info/top_level.txt
jsonpare-0.2.8.dist-info/WHEEL
