Metadata-Version: 2.0
Name: jsonpare
Version: 0.2.8
Summary: A very simple utility to decode and unwind JSON into JSON from the command-line.
Home-page: https://github.com/dsoprea/JsonPare
Author: Dustin Oprea
Author-email: myselfasunder@gmail.com
License: GPL 2
Keywords: json commandline command-line
Platform: UNKNOWN
